pydecor/__init__.py
pydecor/_memoization.py
pydecor/_version.py
pydecor/caches.py
pydecor/constants.py
pydecor/functions.py
pydecor/decorators/__init__.py
pydecor/decorators/_utility.py
pydecor/decorators/_visibility.py
pydecor/decorators/generic.py
pydecor/decorators/ready_to_wear.py
pydecor-2.0.1.dist-info/LICENSE
pydecor-2.0.1.dist-info/METADATA
pydecor-2.0.1.dist-info/WHEEL
pydecor-2.0.1.dist-info/top_level.txt
pydecor-2.0.1.dist-info/RECORD
