Metadata-Version: 2.1
Name: pydecor
Version: 2.0.1
Summary: Easy peasy Python decorators
Home-page: https://github.com/mplanchard/pydecor
Author: Matthew Planchard
Author-email: msplanchard@gmail.com
License: UNKNOWN
Keywords: decorators,python3
Platform: UNKNOWN
Classifier: Development Status :: 5 - Production/Stable
Classifier: Intended Audience :: Developers
Classifier: License :: OSI Approved :: MIT License
Classifier: Natural Language :: English
Classifier: Operating System :: POSIX :: Linux
Classifier: Programming Language :: Python :: 3 :: Only
Classifier: Programming Language :: Python :: 3.6
Classifier: Programming Language :: Python :: 3.7
Classifier: Programming Language :: Python :: 3.8
Classifier: Programming Language :: Python :: Implementation :: PyPy
Requires-Python: >=3.6
Requires-Dist: dill
Requires-Dist: six
Requires-Dist: typing ; python_version < "3.5"
Provides-Extra: dev
Requires-Dist: coverage ; extra == 'dev'
Requires-Dist: pytest (>=4.6) ; extra == 'dev'
Requires-Dist: tox ; extra == 'dev'
Requires-Dist: wheel ; extra == 'dev'
Requires-Dist: flake8 ; (implementation_name == "cpython") and extra == 'dev'
Requires-Dist: ipdb ; (implementation_name == "cpython") and extra == 'dev'
Requires-Dist: mypy ; (implementation_name == "cpython") and extra == 'dev'
Requires-Dist: pylint ; (implementation_name == "cpython") and extra == 'dev'
Requires-Dist: pytest-cov ; (implementation_name == "cpython") and extra == 'dev'
Requires-Dist: pytest-cov (==2.8.1) ; (implementation_name == "pypy") and extra == 'dev'
Requires-Dist: mock ; (python_version < "3.0") and extra == 'dev'
Requires-Dist: pytest-cov (==2.8.1) ; (python_version <= "3.7") and extra == 'dev'
Requires-Dist: black ; (python_version > "3.5" and implementation_name == "cpython") and extra == 'dev'
